pypublish/__init__.py
pypublish/publisher.py
pypublish/tool.py
pypublish/templates/__init__.py
pypublish/templates/base.txt
pypublish/templates/child.txt
pypublish/templates/css.txt
pypublish/templates/data.hjson
pypublish/templates/header.txt
pypublish/templates/item.py
pypublish/templates/items.hjson
pypublish/templates/items.txt
pypublish/templates/macros.txt
pypublish/templates/parent.txt
pypublish-0.0.49.data/scripts/pypublish_help
pypublish-0.0.49.data/scripts/pypublish_help.cmd
pypublish-0.0.49.data/scripts/pypublish_publish
pypublish-0.0.49.data/scripts/pypublish_publish.cmd
pypublish-0.0.49.data/scripts/pypublish_setup
pypublish-0.0.49.data/scripts/pypublish_setup.cmd
pypublish-0.0.49.dist-info/LICENSE
pypublish-0.0.49.dist-info/METADATA
pypublish-0.0.49.dist-info/WHEEL
pypublish-0.0.49.dist-info/top_level.txt
pypublish-0.0.49.dist-info/RECORD
