Metadata-Version: 2.1
Name: pypublish
Version: 0.0.49
Summary: Python library for publish libraries on github and pypi.
Home-page: https://github.com/tuaplicacionpropia/pypublish
Author: Jesús María Ramos Saky
Author-email: tuaplicacionpropia@gmail.com
License: MIT
Download-URL: https://github.com/tuaplicacionpropia/pypublish/archive/master.zip
Keywords: p,u,b,l,i,s,h,,, ,p,y,p,i,,, ,g,i,t,h,u,b,,, ,l,i,b,r,a,r,y
Platform: any
Classifier: Development Status :: 1 - Planning
Classifier: License :: OSI Approved :: MIT License
Classifier: Programming Language :: Python
Classifier: Programming Language :: Python :: 3
Classifier: Intended Audience :: Developers
Classifier: Topic :: Software Development :: Libraries
Requires-Dist: hjson (>=2.0.2)
Requires-Dist: sbrowser (>=0.0.23)
Requires-Dist: wheel
Requires-Dist: twine
